Metadata-Version: 1.0
Name: classifier-model
Version: 1.0
Summary: efficient 2 class image classfier.
Home-page: UNKNOWN
Author: Gujjar Mohan Manjunath
Author-email: manjunathgujjar.147@gmail.com
License: UNKNOWN
Platform: UNKNOWN
